j1939/__init__.py
j1939/controller_application.py
j1939/electronic_control_unit.py
j1939/message_id.py
j1939/name.py
j1939/parameter_group_number.py
j1939/version.py
j1939-0.1.0.dev1.dist-info/METADATA
j1939-0.1.0.dev1.dist-info/RECORD
j1939-0.1.0.dev1.dist-info/WHEEL
j1939-0.1.0.dev1.dist-info/top_level.txt
