Metadata-Version: 2.1
Name: j1939
Version: 0.1.0.dev1
Summary: SAE J1939 stack implementation
Home-page: https://github.com/benkfra/j1939
Author: Frank Benkert
Author-email: opensource@frank-benkert.de
License: MIT
Keywords: CAN SAE J1939
Platform: any
Classifier: Development Status :: 3 - Alpha
Classifier: License :: OSI Approved :: MIT License
Classifier: Operating System :: OS Independent
Classifier: Programming Language :: Python :: 2
Classifier: Programming Language :: Python :: 3
Classifier: Intended Audience :: Developers
Classifier: Topic :: Scientific/Engineering
Requires-Dist: python-can (>=2.0.0)
